espn_nfl_py/__init__.py
espn_nfl_py/api.py
espn_nfl_py/endpoints.py
espn_nfl_py/exceptions.py
espn_nfl_py-0.1.1.dist-info/METADATA
espn_nfl_py-0.1.1.dist-info/WHEEL
espn_nfl_py-0.1.1.dist-info/top_level.txt
espn_nfl_py-0.1.1.dist-info/RECORD
